ECCFP/__init__.py
ECCFP/main.py
ECCFP/cli/__init__.py
ECCFP/cli/_utils.py
ECCFP/cli/accurate_eccDNA.py
ECCFP/cli/config.py
ECCFP/cli/consensus_variants.py
ECCFP/cli/preprocessing.py
eccfp-1.0.0.dist-info/LICENSE
eccfp-1.0.0.dist-info/METADATA
eccfp-1.0.0.dist-info/WHEEL
eccfp-1.0.0.dist-info/entry_points.txt
eccfp-1.0.0.dist-info/top_level.txt
eccfp-1.0.0.dist-info/RECORD
