Metadata-Version: 2.1
Name: eccfp
Version: 1.0.0
Home-page: 
Author: Li Wang, Zhang Tangxuan
Author-email: 
License-File: LICENSE
Requires-Dist: biopython ==1.85
Requires-Dist: numpy ==1.26.4
Requires-Dist: pandas ==2.3.2
Requires-Dist: pyfaidx ==0.9.0.1
Requires-Dist: pyfastx ==2.2.0
Requires-Dist: rich ==14.1.0
